compyt/__init__.py
compyt/compyt.py
compyt-1.6.dist-info/METADATA
compyt-1.6.dist-info/WHEEL
compyt-1.6.dist-info/top_level.txt
compyt-1.6.dist-info/RECORD
