Metadata-Version: 2.1
Name: compyt
Version: 1.6
Summary: UNKNOWN
Home-page: UNKNOWN
Author: ['Michael Kellman']
Author-email: michael.kellman@ucsf.edu
License: BSD
Platform: UNKNOWN
